dagster_weaviate/__init__.py
dagster_weaviate/config.py
dagster_weaviate/resource.py
dagster_weaviate-0.0.3.dist-info/METADATA
dagster_weaviate-0.0.3.dist-info/WHEEL
dagster_weaviate-0.0.3.dist-info/top_level.txt
dagster_weaviate-0.0.3.dist-info/RECORD
