Metadata-Version: 2.4
Name: dagster-weaviate
Version: 0.0.3
Summary: Dagster integration with Weaviate
Requires-Python: >=3.10
Requires-Dist: dagster>=1.8.0
Requires-Dist: weaviate-client>=4.10.2
